fdp_mcp_server/__init__.py
fdp_mcp_server/__main__.py
fdp_mcp_server/proxy_server.py
fdp_mcp_server/streamable_client.py
fdp_mcp_server-0.1.1.dist-info/licenses/LICENSE
fdp_mcp_server-0.1.1.dist-info/METADATA
fdp_mcp_server-0.1.1.dist-info/WHEEL
fdp_mcp_server-0.1.1.dist-info/entry_points.txt
fdp_mcp_server-0.1.1.dist-info/top_level.txt
fdp_mcp_server-0.1.1.dist-info/RECORD
