Metadata-Version: 2.4
Name: fdp-mcp-server
Version: 0.1.1
Summary: QAX XLab's mcp server
Requires-Python: >=3.13
License-File: LICENSE
Requires-Dist: mcp>=1.9.4
Dynamic: license-file
